nexus/__init__.py
nexus/_nexus_fast.cpython-313-darwin.so
nexus/backends/__init__.py
nexus/backends/backend.py
nexus/backends/base_blob_connector.py
nexus/backends/cache_mixin.py
nexus/backends/gcs.py
nexus/backends/gcs_connector.py
nexus/backends/gdrive_connector.py
nexus/backends/gmail_connector.py
nexus/backends/gmail_connector_utils.py
nexus/backends/hn_connector.py
nexus/backends/local.py
nexus/backends/registry.py
nexus/backends/s3_connector.py
nexus/backends/service_map.py
nexus/backends/x_api_client.py
nexus/backends/x_connector.py
nexus/cli/__init__.py
nexus/cli/commands/__init__.py
nexus/cli/commands/admin.py
nexus/cli/commands/agent.py
nexus/cli/commands/connectors.py
nexus/cli/commands/directory.py
nexus/cli/commands/file_ops.py
nexus/cli/commands/llm.py
nexus/cli/commands/mcp.py
nexus/cli/commands/memory.py
nexus/cli/commands/metadata.py
nexus/cli/commands/mounts.py
nexus/cli/commands/oauth.py
nexus/cli/commands/operations.py
nexus/cli/commands/plugins.py
nexus/cli/commands/rebac.py
nexus/cli/commands/sandbox.py
nexus/cli/commands/search.py
nexus/cli/commands/server.py
nexus/cli/commands/skills.py
nexus/cli/commands/versions.py
nexus/cli/commands/work.py
nexus/cli/commands/workflows.py
nexus/cli/commands/workspace.py
nexus/cli/context.py
nexus/cli/formatters.py
nexus/cli/main.py
nexus/cli/utils.py
nexus/config.py
nexus/core/__init__.py
nexus/core/ace/__init__.py
nexus/core/ace/consolidation.py
nexus/core/ace/curation.py
nexus/core/ace/feedback.py
nexus/core/ace/learning_loop.py
nexus/core/ace/playbook.py
nexus/core/ace/reflection.py
nexus/core/ace/trajectory.py
nexus/core/agents.py
nexus/core/async_bridge.py
nexus/core/async_permissions.py
nexus/core/async_rebac_manager.py
nexus/core/async_scoped_filesystem.py
nexus/core/context_utils.py
nexus/core/docker_image_builder.py
nexus/core/entity_registry.py
nexus/core/exceptions.py
nexus/core/export_import.py
nexus/core/filesystem.py
nexus/core/filters.py
nexus/core/glob_fast.py
nexus/core/grep_fast.py
nexus_ai_fs-0.6.4.dist-info/METADATA
nexus_ai_fs-0.6.4.dist-info/WHEEL
nexus_ai_fs-0.6.4.dist-info/entry_points.txt
nexus_ai_fs-0.6.4.dist-info/licenses/LICENSE
nexus_ai_fs-0.6.4.dist-info/RECORD
