Metadata-Version: 2.4
Name: nexus-ai-fs
Version: 0.6.4
Classifier: Development Status :: 4 - Beta
Classifier: Intended Audience :: Developers
Classifier: License :: OSI Approved :: MIT License
Classifier: Operating System :: OS Independent
Classifier: Programming Language :: Python :: 3
Classifier: Programming Language :: Python :: 3.13
Classifier: Topic :: Software Development :: Libraries :: Python Modules
Classifier: Topic :: System :: Filesystems
Classifier: Topic :: Scientific/Engineering :: Artificial Intelligence
Requires-Dist: click>=8.1.7
Requires-Dist: rich>=13.7.0
Requires-Dist: tqdm>=4.66.0
Requires-Dist: pydantic>=2.5.0
Requires-Dist: pyyaml>=6.0.1
Requires-Dist: httpx>=0.28.1
Requires-Dist: requests>=2.31.0
Requires-Dist: tenacity>=8.2.0
Requires-Dist: fastapi>=0.124.0
Requires-Dist: uvicorn[standard]>=0.38.0
Requires-Dist: uvloop>=0.22.1 ; sys_platform != 'win32'
Requires-Dist: sqlalchemy>=2.0.44
Requires-Dist: alembic>=1.13.0
Requires-Dist: psycopg2-binary>=2.9.10
Requires-Dist: asyncpg>=0.31.0
Requires-Dist: aiosqlite>=0.20.0
Requires-Dist: cachetools>=6.2.2
Requires-Dist: authlib>=1.6.5
Requires-Dist: bcrypt>=4.0.0
Requires-Dist: cryptography>=41.0.0
Requires-Dist: boto3>=1.42.4
Requires-Dist: google-cloud-storage>=3.6.0
Requires-Dist: google-api-python-client>=2.187.0
Requires-Dist: google-auth>=2.43.0
Requires-Dist: google-auth-httplib2>=0.2.1
Requires-Dist: google-auth-oauthlib>=1.2.0
Requires-Dist: markitdown[all]>=0.1.4
Requires-Dist: litellm>=1.0
Requires-Dist: tiktoken>=0.12
Requires-Dist: anthropic>=0.75
Requires-Dist: dotenv>=0.9.9
Requires-Dist: fastmcp>=0.2.0
Requires-Dist: llama-parse>=0.6.88
Requires-Dist: orjson>=3.9.0 ; extra == 'performance'
Requires-Dist: blake3>=0.3.0 ; extra == 'performance'
Requires-Dist: pytest>=7.4.4 ; extra == 'dev'
Requires-Dist: pytest-asyncio>=0.23.3 ; extra == 'dev'
Requires-Dist: pytest-cov>=4.1.0 ; extra == 'dev'
Requires-Dist: pytest-mock>=3.12.0 ; extra == 'dev'
Requires-Dist: pytest-benchmark>=4.0.0 ; extra == 'dev'
Requires-Dist: pytest-xdist>=3.5.0 ; extra == 'dev'
Requires-Dist: freezegun>=1.4.0 ; extra == 'dev'
Requires-Dist: ruff>=0.14.0 ; extra == 'dev'
Requires-Dist: mypy>=1.8.0 ; extra == 'dev'
Requires-Dist: pre-commit>=3.6.0 ; extra == 'dev'
Requires-Dist: mkdocs>=1.5.3 ; extra == 'dev'
Requires-Dist: mkdocs-material>=9.5.0 ; extra == 'dev'
Requires-Dist: mkdocs-git-revision-date-localized-plugin>=1.2.0 ; extra == 'dev'
Requires-Dist: mkdocs-minify-plugin>=0.8.0 ; extra == 'dev'
Requires-Dist: types-pyyaml>=6.0.12 ; extra == 'dev'
Requires-Dist: types-cachetools>=5.3.0 ; extra == 'dev'
Requires-Dist: types-requests>=2.31.0 ; extra == 'dev'
Requires-Dist: pytest>=7.4.4 ; extra == 'test'
Requires-Dist: pytest-asyncio>=0.23.3 ; extra == 'test'
Requires-Dist: pytest-cov>=4.1.0 ; extra == 'test'
Requires-Dist: pytest-mock>=3.12.0 ; extra == 'test'
Requires-Dist: pytest-benchmark>=4.0.0 ; extra == 'test'
Requires-Dist: pytest-xdist>=3.5.0 ; extra == 'test'
Requires-Dist: freezegun>=1.4.0 ; extra == 'test'
Requires-Dist: langchain-core>=0.3.0 ; extra == 'test'
Requires-Dist: langgraph>=0.2.0 ; extra == 'test'
Requires-Dist: fusepy>=3.0.1 ; extra == 'fuse'
Requires-Dist: psycopg2-binary>=2.9.9 ; extra == 'postgres'
Requires-Dist: sqlite-vec>=0.1.0 ; extra == 'semantic-search'
Requires-Dist: pgvector>=0.3.0 ; extra == 'semantic-search'
Requires-Dist: openai>=1.0.0 ; extra == 'semantic-search-remote'
Requires-Dist: fusepy>=3.0.1 ; extra == 'all'
Requires-Dist: psycopg2-binary>=2.9.9 ; extra == 'all'
Requires-Dist: sqlite-vec>=0.1.0 ; extra == 'all'
Requires-Dist: pgvector>=0.3.0 ; extra == 'all'
Requires-Dist: openai>=1.0.0 ; extra == 'all'
Requires-Dist: orjson>=3.9.0 ; extra == 'all'
Provides-Extra: performance
Provides-Extra: dev
Provides-Extra: test
Provides-Extra: fuse
Provides-Extra: postgres
Provides-Extra: semantic-search
Provides-Extra: semantic-search-remote
Provides-Extra: all
License-File: LICENSE
Summary: AI-Native Distributed Filesystem Architecture
Keywords: filesystem,ai,agents,storage,distributed,llm,vector-search,content-addressable
Author-email: Nexus Team <team@nexus.example.com>
Maintainer-email: Nexus Team <team@nexus.example.com>
License: MIT
Requires-Python: >=3.13
Project-URL: Homepage, https://github.com/nexi-lab/nexus
Project-URL: Documentation, https://github.com/nexi-lab/nexus/blob/main/README.md
Project-URL: Repository, https://github.com/nexi-lab/nexus
Project-URL: Issues, https://github.com/nexi-lab/nexus/issues
Project-URL: Changelog, https://github.com/nexi-lab/nexus/blob/main/CHANGELOG.md
